{
  "project_info": {
    "project_number": "1073348767110",
    "firebase_url": "https://merge-shooter-33180171.firebaseio.com",
    "project_id": "merge-shooter-33180171",
    "storage_bucket": "merge-shooter-33180171.appspot.com"
  },
  "client": [
    {
      "client_info": {
        "mobilesdk_app_id": "1:1073348767110:android:0eedb49c50986edf",
        "android_client_info": {
          "package_name": "pier.android.mergeshooter"
        }
      },
      "oauth_client": [
        {
          "client_id": "1073348767110-7snu60u22lmdj3mrhn206k9svgn8kvq7.apps.googleusercontent.com",
          "client_type": 3
        }
      ],
      "api_key": [
        {
          "current_key": "AIzaSyCeKMPIyJ_rx6Hkadqewz7Kd6BLfKBAe60"
        }
      ],
      "services": {
        "appinvite_service": {
          "other_platform_oauth_client": [
            {
              "client_id": "1073348767110-7snu60u22lmdj3mrhn206k9svgn8kvq7.apps.googleusercontent.com",
              "client_type": 3
            },
            {
              "client_id": "1073348767110-2v9o3mdblnh6hpln025i5c0nt3ugfhf6.apps.googleusercontent.com",
              "client_type": 2,
              "ios_info": {
                "bundle_id": "pier.ios.mergeshooter"
              }
            }
          ]
        }
      },
      "admob_app_id": "ca-app-pub-8118299571958162~8122476647"
    }
  ],
  "configuration_version": "1"
}